datewise/__init__.py
datewise/datewise.py
datewise-1.0.0.dist-info/METADATA
datewise-1.0.0.dist-info/WHEEL
datewise-1.0.0.dist-info/top_level.txt
datewise-1.0.0.dist-info/RECORD
