Metadata-Version: 2.1
Name: datewise
Version: 1.0.0
Summary: Thesis Library
Home-page: https://datewise.readthedocs.io/
Author: Sebastian Gontkovic
Author-email: sebascngont@gmail.com
License: MIT
Classifier: Intended Audience :: Developers
Classifier: License :: OSI Approved :: MIT License
Classifier: Programming Language :: Python
Classifier: Programming Language :: Python :: 3.9
Classifier: Programming Language :: Python :: 3.10
Classifier: Programming Language :: Python :: 3.11
Classifier: Programming Language :: Python :: 3.12
Classifier: Operating System :: OS Independent
Requires-Dist: pandas
Requires-Dist: numpy
Requires-Dist: python-dateutil
Requires-Dist: pytest
